ids_iforest/__init__.py
ids_iforest/capture.py
ids_iforest/detect.py
ids_iforest/logging_utils.py
ids_iforest/pcap2flows.py
ids_iforest/train.py
ids_iforest/utils.py
ids_iforest/scripts/__init__.py
ids_iforest/scripts/generate_datasets.py
ids_iforest/scripts/prepare_csecic2018.py
ids_iforest-0.1.0.dist-info/licenses/LICENSE
ids_iforest-0.1.0.dist-info/METADATA
ids_iforest-0.1.0.dist-info/WHEEL
ids_iforest-0.1.0.dist-info/entry_points.txt
ids_iforest-0.1.0.dist-info/top_level.txt
ids_iforest-0.1.0.dist-info/RECORD
